whichaxis/__init__.py
whichaxis/array.py
whichaxis/reducers.py
whichaxis-0.1.4.dist-info/METADATA
whichaxis-0.1.4.dist-info/WHEEL
whichaxis-0.1.4.dist-info/licenses/LICENSE
whichaxis-0.1.4.dist-info/RECORD
