Metadata-Version: 2.4
Name: whichaxis
Version: 0.1.4
Summary: NumPy arrays with named axes. Because axis=1 is not a memory aid.
License: MIT
License-File: LICENSE
Keywords: numpy,labeled-arrays,scientific-computing,performance,xarray
Author: Gaudenz Halter
Requires-Python: >=3.10,<4.0
Classifier: Development Status :: 3 - Alpha
Classifier: Intended Audience :: Science/Research
Classifier: License :: OSI Approved :: MIT License
Classifier: Programming Language :: Python :: 3
Classifier: Programming Language :: Python :: 3.10
Classifier: Programming Language :: Python :: 3.11
Classifier: Programming Language :: Python :: 3.12
Classifier: Programming Language :: Python :: 3.13
Classifier: Programming Language :: Python :: 3.14
Classifier: Topic :: Scientific/Engineering
Requires-Dist: numpy (>=1.23)
Requires-Dist: xarray (>=2023.1)
Project-URL: Homepage, https://github.com/ghalter/whichaxis
Project-URL: Repository, https://github.com/ghalter/whichaxis
